syaz0.cpython-38-x86_64-linux-gnu.so
syaz0-1.0.1.dist-info/WHEEL
syaz0-1.0.1.dist-info/top_level.txt
syaz0-1.0.1.dist-info/RECORD
syaz0-1.0.1.dist-info/METADATA
