Metadata-Version: 2.1
Name: syaz0
Version: 1.0.1
Summary: Library for data compression using Nintendo's Yaz0 algorithm
Home-page: https://github.com/zeldamods/syaz0
Author: leoetlino
Author-email: leo@leolam.fr
License: UNKNOWN
Platform: UNKNOWN
Classifier: License :: OSI Approved :: GNU General Public License v2 or later (GPLv2+)
Classifier: Topic :: Software Development :: Libraries
Classifier: Operating System :: OS Independent
Classifier: Programming Language :: C++
Classifier: Programming Language :: Python :: 3 :: Only
Requires-Python: >=3.6
